meds_etl_cpp.cpython-39-x86_64-linux-gnu.so
meds_etl_cpp-0.3.4.dist-info/METADATA
meds_etl_cpp-0.3.4.dist-info/WHEEL
meds_etl_cpp-0.3.4.dist-info/top_level.txt
meds_etl_cpp-0.3.4.dist-info/RECORD
meds_etl_cpp-0.3.4.dist-info/licenses/LICENSE
