Metadata-Version: 2.4
Name: meds_etl_cpp
Version: 0.3.4
Summary: Optimized algorithms for meds_etl implemented in C++.
License-Expression: Apache-2.0
Requires-Python: >3.9
License-File: LICENSE
Dynamic: license-file
